setup.py
wgetplus/__init__.py
wgetplus/wgetplus
wgetplus.egg-info/PKG-INFO
wgetplus.egg-info/SOURCES.txt
wgetplus.egg-info/dependency_links.txt
wgetplus.egg-info/not-zip-safe
wgetplus.egg-info/top_level.txt