Metadata-Version: 1.0
Name: wgetplus
Version: 0.0.0
Summary: Extended web downloader
Home-page: https://gitlab.fit.cvut.cz/wca/wgetplus
Author: Pavel Petržela
Author-email: pavel@petrzela.eu
License: MIT
Platform: UNKNOWN
